pycolint/__init__.py
pycolint/error_msgs.py
pycolint/main.py
pycolint/msg_types.py
pycolint/parser.py
pycolint/problem_types.py
pycolint/py.typed
pycolint/tokenizer.py
pycolint-0.2.0.dist-info/METADATA
pycolint-0.2.0.dist-info/WHEEL
pycolint-0.2.0.dist-info/entry_points.txt
pycolint-0.2.0.dist-info/RECORD
