Metadata-Version: 2.3
Name: pycolint
Version: 0.2.0
Summary: Add your description here
Requires-Python: >=3.10
